ordered_demuxer/__init__.py
ordered_demuxer/py.typed
ordered_demuxer-0.1.0.dist-info/METADATA
ordered_demuxer-0.1.0.dist-info/WHEEL
ordered_demuxer-0.1.0.dist-info/top_level.txt
ordered_demuxer-0.1.0.dist-info/RECORD
