Metadata-Version: 2.1
Name: ordered-demuxer
Version: 0.1.0
Summary: Break iterators into ordered chunks
Home-page: https://github.com/lissahyacinth/ordered_demuxer
License: MIT
Platform: UNKNOWN
Provides-Extra: dev
Requires-Dist: pytest ; extra == 'dev'
